torch_vision-0.1.6.dev0.dist-info/DESCRIPTION.rst
torch_vision-0.1.6.dev0.dist-info/METADATA
torch_vision-0.1.6.dev0.dist-info/RECORD
torch_vision-0.1.6.dev0.dist-info/WHEEL
torch_vision-0.1.6.dev0.dist-info/metadata.json
torch_vision-0.1.6.dev0.dist-info/top_level.txt
torch_vision-0.1.6.dev0.dist-info/zip-safe
torchvision/__init__.py
torchvision/transforms.py
torchvision/utils.py
torchvision/datasets/__init__.py
torchvision/datasets/cifar.py
torchvision/datasets/coco.py
torchvision/datasets/folder.py
torchvision/datasets/lsun.py
torchvision/datasets/mnist.py
torchvision/models/__init__.py
torchvision/models/alexnet.py
torchvision/models/resnet.py
torchvision/models/vgg.py
