Metadata-Version: 2.0
Name: torch-vision
Version: 0.1.6.dev0
Summary: image and video datasets and models for torch deep learning
Home-page: https://github.com/pytorch/vision
Author: PyTorch Core Team
Author-email: soumith@pytorch.org
License: BSD
Platform: UNKNOWN
